pyintesishome2/__init__.py
pyintesishome2/const.py
pyintesishome2/exceptions.py
pyintesishome2/helpers.py
pyintesishome2/intesisbase.py
pyintesishome2/intesisbox.py
pyintesishome2/intesishome.py
pyintesishome2/intesishomelocal.py
pyintesishome2-1.8.9.dist-info/licenses/LICENSE
pyintesishome2-1.8.9.dist-info/METADATA
pyintesishome2-1.8.9.dist-info/WHEEL
pyintesishome2-1.8.9.dist-info/top_level.txt
pyintesishome2-1.8.9.dist-info/RECORD
