Metadata-Version: 2.4
Name: pyintesishome2
Version: 1.8.9
Summary: A python3 library for running asynchronus communications with IntesisHome Smart AC Controllers
Home-page: https://github.com/dolkensp/pyIntesisHome
Author: James Nimmo
Author-email: james@nimmo.net.nz
License: MIT
Classifier: Development Status :: 3 - Alpha
Classifier: Programming Language :: Python :: 3.4
Classifier: Programming Language :: Python :: 3.5
Classifier: Topic :: Scientific/Engineering :: Interface Engine/Protocol Translator
License-File: LICENSE
Requires-Dist: aiohttp<4,>=3.7.4
Dynamic: author
Dynamic: author-email
Dynamic: classifier
Dynamic: description
Dynamic: description-content-type
Dynamic: home-page
Dynamic: license
Dynamic: license-file
Dynamic: requires-dist
Dynamic: summary
